.travis.yml
README.rst
bootstrap.py
buildout.cfg
pre-commit-check.sh
setup.cfg
setup.py
validation-files.yaml
validation-options.yaml
docs/HISTORY.rst
docs/LICENSE.rst
docs/api.rst
docs/conf.py
docs/conventions.rst
docs/env.rst
docs/index.rst
docs/release.rst
src/chimprewriter/__init__.py
src/chimprewriter/exceptions.py
src/chimprewriter.egg-info/PKG-INFO
src/chimprewriter.egg-info/SOURCES.txt
src/chimprewriter.egg-info/dependency_links.txt
src/chimprewriter.egg-info/not-zip-safe
src/chimprewriter.egg-info/requires.txt
src/chimprewriter.egg-info/top_level.txt
src/chimprewriter/tests/__init__.py
src/chimprewriter/tests/test_chimprewriter.py