Metadata-Version: 1.1
Name: chimprewriter
Version: 0.1
Summary: Python bindings for ChimpRewriter API
Home-page: http://www.niteoweb.com
Author: NiteoWeb Ltd.
Author-email: info@niteoweb.com
License: BSD
Keywords: API spinner ChimpRewriter
Platform: UNKNOWN
Classifier: Programming Language :: Python
Classifier: Topic :: Internet :: WWW/HTTP
